funda/__init__.py
funda/funda.py
funda/listing.py
funda/py.typed
pyfunda-2.3.0.dist-info/METADATA
pyfunda-2.3.0.dist-info/WHEEL
pyfunda-2.3.0.dist-info/licenses/LICENSE
pyfunda-2.3.0.dist-info/RECORD
