Metadata-Version: 2.4
Name: pyfunda
Version: 2.3.0
Summary: Python API for Funda.nl real estate listings
Project-URL: Homepage, https://github.com/0xMH/pyfunda
Project-URL: Repository, https://github.com/0xMH/pyfunda
Project-URL: Issues, https://github.com/0xMH/pyfunda/issues
Author: 0xMH
License-Expression: AGPL-3.0-or-later
License-File: LICENSE
Keywords: api,funda,housing,netherlands,real-estate,scraper
Classifier: Development Status :: 4 - Beta
Classifier: Intended Audience :: Developers
Classifier: License :: OSI Approved :: GNU Affero General Public License v3 or later (AGPLv3+)
Classifier: Programming Language :: Python :: 3
Classifier: Programming Language :: Python :: 3.10
Classifier: Programming Language :: Python :: 3.11
Classifier: Programming Language :: Python :: 3.12
Requires-Python: >=3.10
Requires-Dist: curl-cffi>=0.14.0
Requires-Dist: tls-client>=1.0.1
Requires-Dist: typing-extensions>=4.0.0
